seekme/__init__.py
seekme/_defaults.py
seekme/client.py
seekme/exceptions.py
seekme/registry.py
seekme/types.py
seekme/db/__init__.py
seekme/db/core.py
seekme/db/drivers/__init__.py
seekme/db/drivers/_seekdb_sql.py
seekme/db/drivers/seekdb.py
seekme/db/drivers/sql.py
seekme/embeddings/__init__.py
seekme/embeddings/base.py
seekme/embeddings/local.py
seekme/embeddings/remote.py
seekme/vector/__init__.py
seekme/vector/core.py
seekme/vector/sql.py
seekme-0.0.1.dist-info/METADATA
seekme-0.0.1.dist-info/WHEEL
seekme-0.0.1.dist-info/licenses/LICENSE
seekme-0.0.1.dist-info/RECORD
