Metadata-Version: 2.3
Name: seekme
Version: 0.0.1
Summary: End-to-end seekdb toolchain for AI workflows in-database.
Project-URL: Homepage, https://psiace.github.io/seekme/
Project-URL: Repository, https://github.com/psiace/seekme
Project-URL: Documentation, https://psiace.github.io/seekme/
Author-email: Chojan Shang <psiace@apache.org>
License-File: LICENSE
Keywords: python
Classifier: Intended Audience :: Developers
Classifier: Programming Language :: Python
Classifier: Programming Language :: Python :: 3
Classifier: Programming Language :: Python :: 3.10
Classifier: Programming Language :: Python :: 3.11
Classifier: Programming Language :: Python :: 3.12
Classifier: Programming Language :: Python :: 3.13
Classifier: Programming Language :: Python :: 3.14
Classifier: Topic :: Software Development :: Libraries :: Python Modules
Requires-Python: <4.0,>=3.10
Requires-Dist: sqlalchemy<3.0,>=2.0.0
Provides-Extra: local-embeddings
Requires-Dist: sentence-transformers<4.0,>=3.0.0; extra == 'local-embeddings'
Provides-Extra: mysql
Requires-Dist: pymysql>=1.1.0; extra == 'mysql'
Provides-Extra: remote-embeddings
Requires-Dist: any-llm-sdk>=1.7.0; (python_version >= '3.11') and extra == 'remote-embeddings'
Provides-Extra: seekdb
Requires-Dist: pylibseekdb; (sys_platform == 'linux') and extra == 'seekdb'
